{
  "name": "KuksaParticipant",
  "base": "PersistedModel",
  "idInjection": false,
  "options": {
    "validateUpsert": true,
    "postgresql": {
      "schema": "public",
      "table": "kuksa_participant"
    }
  },
  "properties": {
    "id": {
      "type": "Number",
      "id": true,
      "generated": false,
      "postgresql": {
        "columnName": "participant_id",
        "dataType": "integer",
        "dataLength": null,
        "dataPrecision": 32,
        "dataScale": 0,
        "nullable": "NO"
      }
    },
    "firstName": {
      "type": "string",
      "required": true,
      "postgresql": {
        "columnName": "first_name",
        "dataType": "character varying",
        "dataLength": 255,
        "dataPrecision": null,
        "dataScale": null,
        "nullable": "NO"
      }
    },
    "lastName": {
      "type": "string",
      "required": true,
      "postgresql": {
        "columnName": "last_name",
        "dataType": "character varying",
        "dataLength": 255,
        "dataPrecision": null,
        "dataScale": null,
        "nullable": "NO"
      }
    },
    "memberNumber": {
      "type": "string",
      "postgresql": {
        "columnName": "member_number",
        "dataType": "character varying",
        "dataLength": 255,
        "dataPrecision": null,
        "dataScale": null,
        "nullable": "YES"
      }
    },
    "dateOfBirth": {
      "type": "date",
      "postgresql": {
        "columnName": "date_of_birth",
        "dataType": "timestamp with time zone",
        "dataLength": null,
        "dataPrecision": null,
        "dataScale": null,
        "nullable": "NO"
      }
    },
    "phoneNumber": {
      "type": "string",
      "postgresql": {
        "columnName": "phone_number",
        "dataType": "character varying",
        "dataLength": 255,
        "dataPrecision": null,
        "dataScale": null,
        "nullable": "YES"
      }
    },
    "email": {
      "type": "string",
      "postgresql": {
        "columnName": "email",
        "dataType": "character varying",
        "dataLength": 255,
        "dataPrecision": null,
        "dataScale": null,
        "nullable": "YES"
      }
    },
    "localGroup": {
      "type": "number",
      "postgresql": {
        "columnName": "local_group",
        "dataType": "integer",
        "dataLength": null,
        "dataPrecision": 32,
        "dataScale": 0,
        "nullable": "YES"
      }
    },
    "campGroup": {
      "type": "number",
      "postgresql": {
        "columnName": "camp_group",
        "dataType": "integer",
        "dataLength": null,
        "dataPrecision": 32,
        "dataScale": 0,
        "nullable": "YES"
      }
    },
    "subCamp": {
      "type": "number",
      "postgresql": {
        "columnName": "sub_camp",
        "dataType": "integer",
        "dataLength": null,
        "dataPrecision": 32,
        "dataScale": 0,
        "nullable": "YES"
      }
    }
  },
  "validations": [],
  "relations": {},
  "acls": [
    {
      "accessType": "*",
      "principalType": "ROLE",
      "principalId": "$everyone",
      "permission": "DENY"
    }
  ],
  "methods": []
}
